bypassAV/__init__.py
bypassAV/setting.py
bypassAV-0.0.1.dist-info/LICENSE
bypassAV-0.0.1.dist-info/METADATA
bypassAV-0.0.1.dist-info/WHEEL
bypassAV-0.0.1.dist-info/top_level.txt
bypassAV-0.0.1.dist-info/RECORD
