Metadata-Version: 2.1
Name: bypassAV
Version: 0.0.1
Summary: CNMB
Author-email: NMSL <CNM@example.com>
License: Copyright (c) 2022 The Python Packaging Authority        
Project-URL: Homepage, https://github.com/pypa/sampleproject
Project-URL: Bug Tracker, https://github.com/pypa/sampleproject/issues
Classifier: Programming Language :: Python :: 3
Classifier: License :: OSI Approved :: MIT License
Classifier: Operating System :: OS Independent
Requires-Python: >=2.7
License-File: LICENSE
